yirifi_ops_code_claude_agent/__init__.py
yirifi_ops_code_claude_agent/agent.py
yirifi_ops_code_claude_agent/config.py
yirifi_ops_code_claude_agent/executor.py
yirifi_ops_code_claude_agent/run.py
yirifi_ops_code_claude_agent/stream_parser.py
yirifi_ops_code_claude_agent/modes/__init__.py
yirifi_ops_code_claude_agent/modes/polling.py
yirifi_ops_code_claude_agent/modes/websocket.py
yirifi_ops_code_claude_agent-0.1.5.dist-info/METADATA
yirifi_ops_code_claude_agent-0.1.5.dist-info/WHEEL
yirifi_ops_code_claude_agent-0.1.5.dist-info/entry_points.txt
yirifi_ops_code_claude_agent-0.1.5.dist-info/RECORD
