Metadata-Version: 2.4
Name: yirifi-ops-code-claude-agent
Version: 0.1.5
Summary: Claude Code Agent for Yirifi Ops Dashboard - AI-assisted coding task execution
Project-URL: Homepage, https://github.com/yirifi/yirifi-ops-code-claude-agent
Project-URL: Repository, https://github.com/yirifi/yirifi-ops-code-claude-agent
Author-email: Yirifi <dev@yirifi.com>
License: MIT
Keywords: agent,ai,automation,claude
Classifier: Development Status :: 3 - Alpha
Classifier: Intended Audience :: Developers
Classifier: License :: OSI Approved :: MIT License
Classifier: Programming Language :: Python :: 3
Classifier: Programming Language :: Python :: 3.11
Classifier: Programming Language :: Python :: 3.12
Requires-Python: >=3.11
Requires-Dist: python-socketio[client]>=5.0.0
Requires-Dist: redis>=4.0.0
Requires-Dist: requests>=2.28.0
Provides-Extra: dev
Requires-Dist: mypy>=1.0.0; extra == 'dev'
Requires-Dist: pytest-asyncio>=0.21.0; extra == 'dev'
Requires-Dist: pytest>=7.0.0; extra == 'dev'
Requires-Dist: ruff>=0.1.0; extra == 'dev'
